labelmerge/config/snakebids.yml
labelmerge/pipeline_description.json
labelmerge/run.py
labelmerge/workflow/Snakefile
labelmerge/workflow/rules/label_harmonization.smk
labelmerge/workflow/scripts/labelmerge.py
labelmerge-0.4.7.dist-info/METADATA
labelmerge-0.4.7.dist-info/WHEEL
labelmerge-0.4.7.dist-info/entry_points.txt
labelmerge-0.4.7.dist-info/RECORD
