Metadata-Version: 2.1
Name: labelmerge
Version: 0.4.7
Summary: Snakebids app for merging multiple label maps.
Author: Jason Kai
Author-email: tkai@uwo.ca
Requires-Python: >=3.8,<3.12
Classifier: Programming Language :: Python :: 3
Classifier: Programming Language :: Python :: 3.8
Classifier: Programming Language :: Python :: 3.9
Classifier: Programming Language :: Python :: 3.10
Classifier: Programming Language :: Python :: 3.11
Requires-Dist: nibabel (>=3.2.2,<4.0.0)
Requires-Dist: numpy (>=1.22.3,<2.0.0)
Requires-Dist: pulp (<2.8.0)
Requires-Dist: snakebids (>=0.10.2,<0.11.0)
Requires-Dist: xarray (>=2022.11.0,<2023.0.0)
